[
  {
    "id": "2026-01-30-更新脚本测试",
    "title": "更新脚本测试",
    "date": "2026年1月30日",
    "readTime": "1",
    "mood": "思考",
    "tags": [
      "随笔"
    ],
    "summary": "测试脚本中"
  },
  {
    "id": "2024-09-28-篮球与少年",
    "title": "篮球与少年",
    "date": "2024年9月28日",
    "readTime": "1分钟阅读",
    "mood": "怀念",
    "tags": [
      "\\[生活",
      "随笔"
    ],
    "summary": "那些篮球场上的的少年人可能并没有小说男主般的帅气。"
  },
  {
    "id": "2026-01-29-发布脚本的测试",
    "title": "发布脚本的测试",
    "date": "2026年1月29日",
    "readTime": "1分钟阅读",
    "mood": "思考",
    "tags": [
      "生活",
      "随笔"
    ],
    "summary": "捣鼓中。"
  },
  {
    "id": "2026-01-30-hello-world",
    "title": "Hello World！我的小站开张了",
    "date": "2026年1月30日",
    "readTime": "2分钟阅读",
    "mood": "期待",
    "tags": [
      "建站",
      "日常"
    ],
    "summary": "终于把这个属于自己的小角落搭建起来了...",
    "keywords": [
      "博客",
      "GitHub Pages",
      "静态网站"
    ]
  }
]